{"batchcomplete": "", "query": {"pages": {"119242": {"pageid": 119242, "ns": 0, "title": "Allen Park, Michigan", "contentmodel": "wikitext", "pagelanguage": "en", "pagelanguagehtmlcode": "en", "pagelanguagedir": "ltr", "touched": "2023-10-10T22:35:47Z", "lastrevid": 1171048867, "length": 19577, "talkid": 2299678, "fullurl": "https://en.wikipedia.org/wiki/Allen_Park,_Michigan", "editurl": "https://en.wikipedia.org/w/index.php?title=Allen_Park,_Michigan&action=edit", "canonicalurl": "https://en.wikipedia.org/wiki/Allen_Park,_Michigan"}}}}