{"batchcomplete": "", "query": {"pages": {"100811": {"pageid": 100811, "ns": 0, "title": "Allgood, Alabama", "contentmodel": "wikitext", "pagelanguage": "en", "pagelanguagehtmlcode": "en", "pagelanguagedir": "ltr", "touched": "2023-10-10T22:35:35Z", "lastrevid": 1165909718, "length": 11278, "talkid": 281031, "fullurl": "https://en.wikipedia.org/wiki/Allgood,_Alabama", "editurl": "https://en.wikipedia.org/w/index.php?title=Allgood,_Alabama&action=edit", "canonicalurl": "https://en.wikipedia.org/wiki/Allgood,_Alabama"}}}}