{"batchcomplete": "", "query": {"pages": {"114226": {"pageid": 114226, "ns": 0, "title": "Alton, Iowa", "contentmodel": "wikitext", "pagelanguage": "en", "pagelanguagehtmlcode": "en", "pagelanguagedir": "ltr", "touched": "2023-10-10T22:35:43Z", "lastrevid": 1171327641, "length": 12617, "talkid": 6862254, "fullurl": "https://en.wikipedia.org/wiki/Alton,_Iowa", "editurl": "https://en.wikipedia.org/w/index.php?title=Alton,_Iowa&action=edit", "canonicalurl": "https://en.wikipedia.org/wiki/Alton,_Iowa"}}}}