{"batchcomplete": "", "query": {"pages": {"131031": {"pageid": 131031, "ns": 0, "title": "Arendtsville, Pennsylvania", "contentmodel": "wikitext", "pagelanguage": "en", "pagelanguagehtmlcode": "en", "pagelanguagedir": "ltr", "touched": "2023-10-10T22:35:56Z", "lastrevid": 1157349196, "length": 8376, "talkid": 11209569, "fullurl": "https://en.wikipedia.org/wiki/Arendtsville,_Pennsylvania", "editurl": "https://en.wikipedia.org/w/index.php?title=Arendtsville,_Pennsylvania&action=edit", "canonicalurl": "https://en.wikipedia.org/wiki/Arendtsville,_Pennsylvania"}}}}