{"batchcomplete": "", "query": {"pages": {"129720": {"pageid": 129720, "ns": 0, "title": "Ashville, Ohio", "contentmodel": "wikitext", "pagelanguage": "en", "pagelanguagehtmlcode": "en", "pagelanguagedir": "ltr", "touched": "2023-10-16T08:31:08Z", "lastrevid": 1177448045, "length": 35822, "talkid": 13535625, "fullurl": "https://en.wikipedia.org/wiki/Ashville,_Ohio", "editurl": "https://en.wikipedia.org/w/index.php?title=Ashville,_Ohio&action=edit", "canonicalurl": "https://en.wikipedia.org/wiki/Ashville,_Ohio"}}}}