{"batchcomplete": "", "query": {"pages": {"117369": {"pageid": 117369, "ns": 0, "title": "Bark River Township, Michigan", "contentmodel": "wikitext", "pagelanguage": "en", "pagelanguagehtmlcode": "en", "pagelanguagedir": "ltr", "touched": "2023-10-10T22:35:46Z", "lastrevid": 1174668783, "length": 7980, "talkid": 15951283, "fullurl": "https://en.wikipedia.org/wiki/Bark_River_Township,_Michigan", "editurl": "https://en.wikipedia.org/w/index.php?title=Bark_River_Township,_Michigan&action=edit", "canonicalurl": "https://en.wikipedia.org/wiki/Bark_River_Township,_Michigan"}}}}