{"batchcomplete": "", "query": {"pages": {"107028": {"pageid": 107028, "ns": 0, "title": "Batesville, Arkansas", "contentmodel": "wikitext", "pagelanguage": "en", "pagelanguagehtmlcode": "en", "pagelanguagedir": "ltr", "touched": "2023-10-10T22:35:38Z", "lastrevid": 1176616588, "length": 15971, "talkid": 283138, "fullurl": "https://en.wikipedia.org/wiki/Batesville,_Arkansas", "editurl": "https://en.wikipedia.org/w/index.php?title=Batesville,_Arkansas&action=edit", "canonicalurl": "https://en.wikipedia.org/wiki/Batesville,_Arkansas"}}}}