{"batchcomplete": "", "query": {"pages": {"109524": {"pageid": 109524, "ns": 0, "title": "Bay Lake, Florida", "contentmodel": "wikitext", "pagelanguage": "en", "pagelanguagehtmlcode": "en", "pagelanguagedir": "ltr", "touched": "2023-10-14T21:10:18Z", "lastrevid": 1177962884, "length": 21838, "watchers": 59, "talkid": 1752986, "fullurl": "https://en.wikipedia.org/wiki/Bay_Lake,_Florida", "editurl": "https://en.wikipedia.org/w/index.php?title=Bay_Lake,_Florida&action=edit", "canonicalurl": "https://en.wikipedia.org/wiki/Bay_Lake,_Florida"}}}}