{"batchcomplete": "", "query": {"pages": {"129824": {"pageid": 129824, "ns": 0, "title": "Brewster, Ohio", "contentmodel": "wikitext", "pagelanguage": "en", "pagelanguagehtmlcode": "en", "pagelanguagedir": "ltr", "touched": "2023-10-10T22:35:55Z", "lastrevid": 1168045780, "length": 11196, "talkid": 13795935, "fullurl": "https://en.wikipedia.org/wiki/Brewster,_Ohio", "editurl": "https://en.wikipedia.org/w/index.php?title=Brewster,_Ohio&action=edit", "canonicalurl": "https://en.wikipedia.org/wiki/Brewster,_Ohio"}}}}