{"batchcomplete": "", "query": {"pages": {"107147": {"pageid": 107147, "ns": 0, "title": "Brinkley, Arkansas", "contentmodel": "wikitext", "pagelanguage": "en", "pagelanguagehtmlcode": "en", "pagelanguagedir": "ltr", "touched": "2023-10-10T22:35:38Z", "lastrevid": 1166316475, "length": 17495, "talkid": 283289, "fullurl": "https://en.wikipedia.org/wiki/Brinkley,_Arkansas", "editurl": "https://en.wikipedia.org/w/index.php?title=Brinkley,_Arkansas&action=edit", "canonicalurl": "https://en.wikipedia.org/wiki/Brinkley,_Arkansas"}}}}