{"batchcomplete": "", "query": {"pages": {"136182": {"pageid": 136182, "ns": 0, "title": "Bryson, Texas", "contentmodel": "wikitext", "pagelanguage": "en", "pagelanguagehtmlcode": "en", "pagelanguagedir": "ltr", "touched": "2023-10-16T06:06:47Z", "lastrevid": 1165537502, "length": 12848, "talkid": 6283864, "fullurl": "https://en.wikipedia.org/wiki/Bryson,_Texas", "editurl": "https://en.wikipedia.org/w/index.php?title=Bryson,_Texas&action=edit", "canonicalurl": "https://en.wikipedia.org/wiki/Bryson,_Texas"}}}}