{"batchcomplete": "", "query": {"pages": {"107907": {"pageid": 107907, "ns": 0, "title": "Calimesa, California", "contentmodel": "wikitext", "pagelanguage": "en", "pagelanguagehtmlcode": "en", "pagelanguagedir": "ltr", "touched": "2023-10-13T06:56:56Z", "lastrevid": 1178652198, "length": 23751, "talkid": 7550032, "fullurl": "https://en.wikipedia.org/wiki/Calimesa,_California", "editurl": "https://en.wikipedia.org/w/index.php?title=Calimesa,_California&action=edit", "canonicalurl": "https://en.wikipedia.org/wiki/Calimesa,_California"}}}}