{"batchcomplete": "", "query": {"pages": {"132095": {"pageid": 132095, "ns": 0, "title": "Centralia, Pennsylvania", "contentmodel": "wikitext", "pagelanguage": "en", "pagelanguagehtmlcode": "en", "pagelanguagedir": "ltr", "touched": "2023-10-14T15:56:07Z", "lastrevid": 1180108649, "length": 47714, "watchers": 450, "talkid": 255824, "fullurl": "https://en.wikipedia.org/wiki/Centralia,_Pennsylvania", "editurl": "https://en.wikipedia.org/w/index.php?title=Centralia,_Pennsylvania&action=edit", "canonicalurl": "https://en.wikipedia.org/wiki/Centralia,_Pennsylvania"}}}}