{"batchcomplete": "", "query": {"pages": {"129297": {"pageid": 129297, "ns": 0, "title": "Chardon, Ohio", "contentmodel": "wikitext", "pagelanguage": "en", "pagelanguagehtmlcode": "en", "pagelanguagedir": "ltr", "touched": "2023-10-10T22:35:54Z", "lastrevid": 1178006732, "length": 27104, "watchers": 39, "talkid": 4680174, "fullurl": "https://en.wikipedia.org/wiki/Chardon,_Ohio", "editurl": "https://en.wikipedia.org/w/index.php?title=Chardon,_Ohio&action=edit", "canonicalurl": "https://en.wikipedia.org/wiki/Chardon,_Ohio"}}}}