{"batchcomplete": "", "query": {"pages": {"117041": {"pageid": 117041, "ns": 0, "title": "Chestonia Township, Michigan", "contentmodel": "wikitext", "pagelanguage": "en", "pagelanguagehtmlcode": "en", "pagelanguagedir": "ltr", "touched": "2023-10-15T16:37:39Z", "lastrevid": 1174673543, "length": 7311, "talkid": 15953920, "fullurl": "https://en.wikipedia.org/wiki/Chestonia_Township,_Michigan", "editurl": "https://en.wikipedia.org/w/index.php?title=Chestonia_Township,_Michigan&action=edit", "canonicalurl": "https://en.wikipedia.org/wiki/Chestonia_Township,_Michigan"}}}}