{"batchcomplete": "", "query": {"pages": {"134442": {"pageid": 134442, "ns": 0, "title": "Chesterfield, South Carolina", "contentmodel": "wikitext", "pagelanguage": "en", "pagelanguagehtmlcode": "en", "pagelanguagedir": "ltr", "touched": "2023-10-10T22:35:58Z", "lastrevid": 1172037346, "length": 10397, "talkid": 10776169, "fullurl": "https://en.wikipedia.org/wiki/Chesterfield,_South_Carolina", "editurl": "https://en.wikipedia.org/w/index.php?title=Chesterfield,_South_Carolina&action=edit", "canonicalurl": "https://en.wikipedia.org/wiki/Chesterfield,_South_Carolina"}}}}