{"batchcomplete": "", "query": {"pages": {"131587": {"pageid": 131587, "ns": 0, "title": "Concord Township, Butler County, Pennsylvania", "contentmodel": "wikitext", "pagelanguage": "en", "pagelanguagehtmlcode": "en", "pagelanguagedir": "ltr", "touched": "2023-10-10T22:35:56Z", "lastrevid": 1177320070, "length": 6211, "talkid": 7042949, "fullurl": "https://en.wikipedia.org/wiki/Concord_Township,_Butler_County,_Pennsylvania", "editurl": "https://en.wikipedia.org/w/index.php?title=Concord_Township,_Butler_County,_Pennsylvania&action=edit", "canonicalurl": "https://en.wikipedia.org/wiki/Concord_Township,_Butler_County,_Pennsylvania"}}}}