{"batchcomplete": "", "query": {"pages": {"112983": {"pageid": 112983, "ns": 0, "title": "Earlville, Iowa", "contentmodel": "wikitext", "pagelanguage": "en", "pagelanguagehtmlcode": "en", "pagelanguagedir": "ltr", "touched": "2023-10-10T22:35:43Z", "lastrevid": 1165647574, "length": 10413, "talkid": 6879040, "fullurl": "https://en.wikipedia.org/wiki/Earlville,_Iowa", "editurl": "https://en.wikipedia.org/w/index.php?title=Earlville,_Iowa&action=edit", "canonicalurl": "https://en.wikipedia.org/wiki/Earlville,_Iowa"}}}}