{"batchcomplete": "", "query": {"pages": {"110806": {"pageid": 110806, "ns": 0, "title": "East Cape Girardeau, Illinois", "contentmodel": "wikitext", "pagelanguage": "en", "pagelanguagehtmlcode": "en", "pagelanguagedir": "ltr", "touched": "2023-10-10T22:35:41Z", "lastrevid": 1166990585, "length": 9271, "talkid": 4461577, "fullurl": "https://en.wikipedia.org/wiki/East_Cape_Girardeau,_Illinois", "editurl": "https://en.wikipedia.org/w/index.php?title=East_Cape_Girardeau,_Illinois&action=edit", "canonicalurl": "https://en.wikipedia.org/wiki/East_Cape_Girardeau,_Illinois"}}}}