{"batchcomplete": "", "query": {"pages": {"111411": {"pageid": 111411, "ns": 0, "title": "East Galesburg, Illinois", "contentmodel": "wikitext", "pagelanguage": "en", "pagelanguagehtmlcode": "en", "pagelanguagedir": "ltr", "touched": "2023-10-10T22:35:41Z", "lastrevid": 1155388896, "length": 7007, "talkid": 8675633, "fullurl": "https://en.wikipedia.org/wiki/East_Galesburg,_Illinois", "editurl": "https://en.wikipedia.org/w/index.php?title=East_Galesburg,_Illinois&action=edit", "canonicalurl": "https://en.wikipedia.org/wiki/East_Galesburg,_Illinois"}}}}