{"batchcomplete": "", "query": {"pages": {"131825": {"pageid": 131825, "ns": 0, "title": "East Caln Township, Chester County, Pennsylvania", "contentmodel": "wikitext", "pagelanguage": "en", "pagelanguagehtmlcode": "en", "pagelanguagedir": "ltr", "touched": "2023-10-10T22:35:56Z", "lastrevid": 1157356948, "length": 13649, "talkid": 10334360, "fullurl": "https://en.wikipedia.org/wiki/East_Caln_Township,_Chester_County,_Pennsylvania", "editurl": "https://en.wikipedia.org/w/index.php?title=East_Caln_Township,_Chester_County,_Pennsylvania&action=edit", "canonicalurl": "https://en.wikipedia.org/wiki/East_Caln_Township,_Chester_County,_Pennsylvania"}}}}