{"batchcomplete": "", "query": {"pages": {"121314": {"pageid": 121314, "ns": 0, "title": "Edgerton, Minnesota", "contentmodel": "wikitext", "pagelanguage": "en", "pagelanguagehtmlcode": "en", "pagelanguagedir": "ltr", "touched": "2023-10-10T22:35:49Z", "lastrevid": 1165647807, "length": 11947, "talkid": 25436094, "fullurl": "https://en.wikipedia.org/wiki/Edgerton,_Minnesota", "editurl": "https://en.wikipedia.org/w/index.php?title=Edgerton,_Minnesota&action=edit", "canonicalurl": "https://en.wikipedia.org/wiki/Edgerton,_Minnesota"}}}}