{"batchcomplete": "", "query": {"pages": {"108036": {"pageid": 108036, "ns": 0, "title": "El Cajon, California", "contentmodel": "wikitext", "pagelanguage": "en", "pagelanguagehtmlcode": "en", "pagelanguagedir": "ltr", "touched": "2023-10-15T04:26:59Z", "lastrevid": 1176340963, "length": 36851, "watchers": 76, "talkid": 2410771, "fullurl": "https://en.wikipedia.org/wiki/El_Cajon,_California", "editurl": "https://en.wikipedia.org/w/index.php?title=El_Cajon,_California&action=edit", "canonicalurl": "https://en.wikipedia.org/wiki/El_Cajon,_California"}}}}