{"batchcomplete": "", "query": {"pages": {"111086": {"pageid": 111086, "ns": 0, "title": "Farmer City, Illinois", "contentmodel": "wikitext", "pagelanguage": "en", "pagelanguagehtmlcode": "en", "pagelanguagedir": "ltr", "touched": "2023-10-10T22:35:41Z", "lastrevid": 1172813701, "length": 13020, "talkid": 4405029, "fullurl": "https://en.wikipedia.org/wiki/Farmer_City,_Illinois", "editurl": "https://en.wikipedia.org/w/index.php?title=Farmer_City,_Illinois&action=edit", "canonicalurl": "https://en.wikipedia.org/wiki/Farmer_City,_Illinois"}}}}