{"batchcomplete": "", "query": {"pages": {"115283": {"pageid": 115283, "ns": 0, "title": "Fort Mitchell, Kentucky", "contentmodel": "wikitext", "pagelanguage": "en", "pagelanguagehtmlcode": "en", "pagelanguagedir": "ltr", "touched": "2023-10-10T22:35:44Z", "lastrevid": 1169441165, "length": 10921, "talkid": 6569052, "fullurl": "https://en.wikipedia.org/wiki/Fort_Mitchell,_Kentucky", "editurl": "https://en.wikipedia.org/w/index.php?title=Fort_Mitchell,_Kentucky&action=edit", "canonicalurl": "https://en.wikipedia.org/wiki/Fort_Mitchell,_Kentucky"}}}}