{"batchcomplete": "", "query": {"pages": {"117969": {"pageid": 117969, "ns": 0, "title": "Fowlerville, Michigan", "contentmodel": "wikitext", "pagelanguage": "en", "pagelanguagehtmlcode": "en", "pagelanguagedir": "ltr", "touched": "2023-10-10T22:35:46Z", "lastrevid": 1167017072, "length": 13410, "talkid": 19783951, "fullurl": "https://en.wikipedia.org/wiki/Fowlerville,_Michigan", "editurl": "https://en.wikipedia.org/w/index.php?title=Fowlerville,_Michigan&action=edit", "canonicalurl": "https://en.wikipedia.org/wiki/Fowlerville,_Michigan"}}}}