{"batchcomplete": "", "query": {"pages": {"125712": {"pageid": 125712, "ns": 0, "title": "Franklin Township, Somerset County, New Jersey", "contentmodel": "wikitext", "pagelanguage": "en", "pagelanguagehtmlcode": "en", "pagelanguagedir": "ltr", "touched": "2023-10-14T00:37:11Z", "lastrevid": 1179887242, "length": 116228, "talkid": 4155352, "fullurl": "https://en.wikipedia.org/wiki/Franklin_Township,_Somerset_County,_New_Jersey", "editurl": "https://en.wikipedia.org/w/index.php?title=Franklin_Township,_Somerset_County,_New_Jersey&action=edit", "canonicalurl": "https://en.wikipedia.org/wiki/Franklin_Township,_Somerset_County,_New_Jersey"}}}}