{"batchcomplete": "", "query": {"pages": {"131266": {"pageid": 131266, "ns": 0, "title": "Freedom, Pennsylvania", "contentmodel": "wikitext", "pagelanguage": "en", "pagelanguagehtmlcode": "en", "pagelanguagedir": "ltr", "touched": "2023-10-10T22:35:56Z", "lastrevid": 1176752927, "length": 12561, "talkid": 7057709, "fullurl": "https://en.wikipedia.org/wiki/Freedom,_Pennsylvania", "editurl": "https://en.wikipedia.org/w/index.php?title=Freedom,_Pennsylvania&action=edit", "canonicalurl": "https://en.wikipedia.org/wiki/Freedom,_Pennsylvania"}}}}