{"batchcomplete": "", "query": {"pages": {"117363": {"pageid": 117363, "ns": 0, "title": "Grayling, Michigan", "contentmodel": "wikitext", "pagelanguage": "en", "pagelanguagehtmlcode": "en", "pagelanguagedir": "ltr", "touched": "2023-10-10T22:35:46Z", "lastrevid": 1179374916, "length": 38601, "talkid": 3315928, "fullurl": "https://en.wikipedia.org/wiki/Grayling,_Michigan", "editurl": "https://en.wikipedia.org/w/index.php?title=Grayling,_Michigan&action=edit", "canonicalurl": "https://en.wikipedia.org/wiki/Grayling,_Michigan"}}}}