{"batchcomplete": "", "query": {"pages": {"132487": {"pageid": 132487, "ns": 0, "title": "Greene Township, Erie County, Pennsylvania", "contentmodel": "wikitext", "pagelanguage": "en", "pagelanguagehtmlcode": "en", "pagelanguagedir": "ltr", "touched": "2023-10-10T22:35:57Z", "lastrevid": 1160897630, "length": 7844, "talkid": 16518154, "fullurl": "https://en.wikipedia.org/wiki/Greene_Township,_Erie_County,_Pennsylvania", "editurl": "https://en.wikipedia.org/w/index.php?title=Greene_Township,_Erie_County,_Pennsylvania&action=edit", "canonicalurl": "https://en.wikipedia.org/wiki/Greene_Township,_Erie_County,_Pennsylvania"}}}}