{"batchcomplete": "", "query": {"pages": {"110567": {"pageid": 110567, "ns": 0, "title": "Haiku-Pauwela, Hawaii", "contentmodel": "wikitext", "pagelanguage": "en", "pagelanguagehtmlcode": "en", "pagelanguagedir": "ltr", "touched": "2023-10-10T22:35:41Z", "lastrevid": 1111378416, "length": 8840, "talkid": 1057644, "fullurl": "https://en.wikipedia.org/wiki/Haiku-Pauwela,_Hawaii", "editurl": "https://en.wikipedia.org/w/index.php?title=Haiku-Pauwela,_Hawaii&action=edit", "canonicalurl": "https://en.wikipedia.org/wiki/Haiku-Pauwela,_Hawaii"}}}}