{"batchcomplete": "", "query": {"pages": {"138462": {"pageid": 138462, "ns": 0, "title": "Hamlin, West Virginia", "contentmodel": "wikitext", "pagelanguage": "en", "pagelanguagehtmlcode": "en", "pagelanguagedir": "ltr", "touched": "2023-10-10T22:36:02Z", "lastrevid": 1166180351, "length": 11926, "talkid": 12258141, "fullurl": "https://en.wikipedia.org/wiki/Hamlin,_West_Virginia", "editurl": "https://en.wikipedia.org/w/index.php?title=Hamlin,_West_Virginia&action=edit", "canonicalurl": "https://en.wikipedia.org/wiki/Hamlin,_West_Virginia"}}}}