{"batchcomplete": "", "query": {"pages": {"114110": {"pageid": 114110, "ns": 0, "title": "Harris, Iowa", "contentmodel": "wikitext", "pagelanguage": "en", "pagelanguagehtmlcode": "en", "pagelanguagedir": "ltr", "touched": "2023-10-10T22:35:43Z", "lastrevid": 1165749265, "length": 9639, "talkid": 6878773, "fullurl": "https://en.wikipedia.org/wiki/Harris,_Iowa", "editurl": "https://en.wikipedia.org/w/index.php?title=Harris,_Iowa&action=edit", "canonicalurl": "https://en.wikipedia.org/wiki/Harris,_Iowa"}}}}