{"batchcomplete": "", "query": {"pages": {"125815": {"pageid": 125815, "ns": 0, "title": "Independence Township, New Jersey", "contentmodel": "wikitext", "pagelanguage": "en", "pagelanguagehtmlcode": "en", "pagelanguagedir": "ltr", "touched": "2023-10-13T02:52:50Z", "lastrevid": 1179889831, "length": 48481, "talkid": 17314356, "fullurl": "https://en.wikipedia.org/wiki/Independence_Township,_New_Jersey", "editurl": "https://en.wikipedia.org/w/index.php?title=Independence_Township,_New_Jersey&action=edit", "canonicalurl": "https://en.wikipedia.org/wiki/Independence_Township,_New_Jersey"}}}}