{"batchcomplete": "", "query": {"pages": {"134059": {"pageid": 134059, "ns": 0, "title": "Jefferson Township, Washington County, Pennsylvania", "contentmodel": "wikitext", "pagelanguage": "en", "pagelanguagehtmlcode": "en", "pagelanguagedir": "ltr", "touched": "2023-10-10T22:35:58Z", "lastrevid": 1157436492, "length": 7662, "talkid": 7057789, "fullurl": "https://en.wikipedia.org/wiki/Jefferson_Township,_Washington_County,_Pennsylvania", "editurl": "https://en.wikipedia.org/w/index.php?title=Jefferson_Township,_Washington_County,_Pennsylvania&action=edit", "canonicalurl": "https://en.wikipedia.org/wiki/Jefferson_Township,_Washington_County,_Pennsylvania"}}}}