{"batchcomplete": "", "query": {"pages": {"129785": {"pageid": 129785, "ns": 0, "title": "Kingston, Ohio", "contentmodel": "wikitext", "pagelanguage": "en", "pagelanguagehtmlcode": "en", "pagelanguagedir": "ltr", "touched": "2023-10-10T22:35:55Z", "lastrevid": 1170032288, "length": 9372, "talkid": 12866928, "fullurl": "https://en.wikipedia.org/wiki/Kingston,_Ohio", "editurl": "https://en.wikipedia.org/w/index.php?title=Kingston,_Ohio&action=edit", "canonicalurl": "https://en.wikipedia.org/wiki/Kingston,_Ohio"}}}}