{"batchcomplete": "", "query": {"pages": {"18407744": {"pageid": 18407744, "ns": 0, "title": "Lake Ka-Ho, Illinois", "contentmodel": "wikitext", "pagelanguage": "en", "pagelanguagehtmlcode": "en", "pagelanguagedir": "ltr", "touched": "2023-08-24T20:51:55Z", "lastrevid": 231198115, "length": 66, "redirect": "", "fullurl": "https://en.wikipedia.org/wiki/Lake_Ka-Ho,_Illinois", "editurl": "https://en.wikipedia.org/w/index.php?title=Lake_Ka-Ho,_Illinois&action=edit", "canonicalurl": "https://en.wikipedia.org/wiki/Lake_Ka-Ho,_Illinois"}}}}