{"batchcomplete": "", "query": {"pages": {"150697": {"pageid": 150697, "ns": 0, "title": "Lake, Mississippi", "contentmodel": "wikitext", "pagelanguage": "en", "pagelanguagehtmlcode": "en", "pagelanguagedir": "ltr", "touched": "2023-10-10T22:36:07Z", "lastrevid": 1166205360, "length": 10253, "talkid": 16199020, "fullurl": "https://en.wikipedia.org/wiki/Lake,_Mississippi", "editurl": "https://en.wikipedia.org/w/index.php?title=Lake,_Mississippi&action=edit", "canonicalurl": "https://en.wikipedia.org/wiki/Lake,_Mississippi"}}}}