{"batchcomplete": "", "query": {"pages": {"74939914": {"pageid": 74939914, "ns": 0, "title": "Lower Oxford Township, Chester County, Pennsylvania", "contentmodel": "wikitext", "pagelanguage": "en", "pagelanguagehtmlcode": "en", "pagelanguagedir": "ltr", "touched": "2023-09-29T18:25:23Z", "lastrevid": 1177807630, "length": 96, "redirect": "", "new": "", "talkid": 74939915, "fullurl": "https://en.wikipedia.org/wiki/Lower_Oxford_Township,_Chester_County,_Pennsylvania", "editurl": "https://en.wikipedia.org/w/index.php?title=Lower_Oxford_Township,_Chester_County,_Pennsylvania&action=edit", "canonicalurl": "https://en.wikipedia.org/wiki/Lower_Oxford_Township,_Chester_County,_Pennsylvania"}}}}