{"batchcomplete": "", "query": {"pages": {"129943": {"pageid": 129943, "ns": 0, "title": "Macksburg, Ohio", "contentmodel": "wikitext", "pagelanguage": "en", "pagelanguagehtmlcode": "en", "pagelanguagedir": "ltr", "touched": "2023-10-10T22:35:55Z", "lastrevid": 1167324491, "length": 9683, "talkid": 7665530, "fullurl": "https://en.wikipedia.org/wiki/Macksburg,_Ohio", "editurl": "https://en.wikipedia.org/w/index.php?title=Macksburg,_Ohio&action=edit", "canonicalurl": "https://en.wikipedia.org/wiki/Macksburg,_Ohio"}}}}