{"batchcomplete": "", "query": {"pages": {"131852": {"pageid": 131852, "ns": 0, "title": "Malvern, Pennsylvania", "contentmodel": "wikitext", "pagelanguage": "en", "pagelanguagehtmlcode": "en", "pagelanguagedir": "ltr", "touched": "2023-10-10T22:35:56Z", "lastrevid": 1179414836, "length": 23431, "talkid": 8060705, "fullurl": "https://en.wikipedia.org/wiki/Malvern,_Pennsylvania", "editurl": "https://en.wikipedia.org/w/index.php?title=Malvern,_Pennsylvania&action=edit", "canonicalurl": "https://en.wikipedia.org/wiki/Malvern,_Pennsylvania"}}}}