{"batchcomplete": "", "query": {"pages": {"112911": {"pageid": 112911, "ns": 0, "title": "Marquette, Iowa", "contentmodel": "wikitext", "pagelanguage": "en", "pagelanguagehtmlcode": "en", "pagelanguagedir": "ltr", "touched": "2023-10-10T22:35:43Z", "lastrevid": 1166522863, "length": 10922, "talkid": 6878480, "fullurl": "https://en.wikipedia.org/wiki/Marquette,_Iowa", "editurl": "https://en.wikipedia.org/w/index.php?title=Marquette,_Iowa&action=edit", "canonicalurl": "https://en.wikipedia.org/wiki/Marquette,_Iowa"}}}}