{"batchcomplete": "", "query": {"pages": {"138365": {"pageid": 138365, "ns": 0, "title": "Martinsburg, West Virginia", "contentmodel": "wikitext", "pagelanguage": "en", "pagelanguagehtmlcode": "en", "pagelanguagedir": "ltr", "touched": "2023-10-10T22:36:02Z", "lastrevid": 1177362638, "length": 38533, "watchers": 48, "talkid": 11622090, "fullurl": "https://en.wikipedia.org/wiki/Martinsburg,_West_Virginia", "editurl": "https://en.wikipedia.org/w/index.php?title=Martinsburg,_West_Virginia&action=edit", "canonicalurl": "https://en.wikipedia.org/wiki/Martinsburg,_West_Virginia"}}}}