{"batchcomplete": "", "query": {"pages": {"114088": {"pageid": 114088, "ns": 0, "title": "Melrose, Iowa", "contentmodel": "wikitext", "pagelanguage": "en", "pagelanguagehtmlcode": "en", "pagelanguagedir": "ltr", "touched": "2023-10-10T22:35:43Z", "lastrevid": 1165893108, "length": 11743, "talkid": 6878431, "fullurl": "https://en.wikipedia.org/wiki/Melrose,_Iowa", "editurl": "https://en.wikipedia.org/w/index.php?title=Melrose,_Iowa&action=edit", "canonicalurl": "https://en.wikipedia.org/wiki/Melrose,_Iowa"}}}}