{"batchcomplete": "", "query": {"pages": {"151160": {"pageid": 151160, "ns": 0, "title": "Mesquite, Texas", "contentmodel": "wikitext", "pagelanguage": "en", "pagelanguagehtmlcode": "en", "pagelanguagedir": "ltr", "touched": "2023-10-13T06:56:56Z", "lastrevid": 1178408918, "length": 43042, "watchers": 75, "talkid": 4512299, "fullurl": "https://en.wikipedia.org/wiki/Mesquite,_Texas", "editurl": "https://en.wikipedia.org/w/index.php?title=Mesquite,_Texas&action=edit", "canonicalurl": "https://en.wikipedia.org/wiki/Mesquite,_Texas"}}}}