{"batchcomplete": "", "query": {"pages": {"106927": {"pageid": 106927, "ns": 0, "title": "Monette, Arkansas", "contentmodel": "wikitext", "pagelanguage": "en", "pagelanguagehtmlcode": "en", "pagelanguagedir": "ltr", "touched": "2023-10-10T22:35:38Z", "lastrevid": 1165893913, "length": 10835, "talkid": 283032, "fullurl": "https://en.wikipedia.org/wiki/Monette,_Arkansas", "editurl": "https://en.wikipedia.org/w/index.php?title=Monette,_Arkansas&action=edit", "canonicalurl": "https://en.wikipedia.org/wiki/Monette,_Arkansas"}}}}