{"batchcomplete": "", "query": {"pages": {"74850976": {"pageid": 74850976, "ns": 0, "title": "Morgan Township, Greene County, Pennsylvania", "contentmodel": "wikitext", "pagelanguage": "en", "pagelanguagehtmlcode": "en", "pagelanguagedir": "ltr", "touched": "2023-09-18T14:40:19Z", "lastrevid": 1175956188, "length": 90, "redirect": "", "new": "", "talkid": 74850977, "fullurl": "https://en.wikipedia.org/wiki/Morgan_Township,_Greene_County,_Pennsylvania", "editurl": "https://en.wikipedia.org/w/index.php?title=Morgan_Township,_Greene_County,_Pennsylvania&action=edit", "canonicalurl": "https://en.wikipedia.org/wiki/Morgan_Township,_Greene_County,_Pennsylvania"}}}}