{"batchcomplete": "", "query": {"pages": {"110842": {"pageid": 110842, "ns": 0, "title": "Neponset, Illinois", "contentmodel": "wikitext", "pagelanguage": "en", "pagelanguagehtmlcode": "en", "pagelanguagedir": "ltr", "touched": "2023-10-10T22:35:41Z", "lastrevid": 1176762322, "length": 8340, "talkid": 8679160, "fullurl": "https://en.wikipedia.org/wiki/Neponset,_Illinois", "editurl": "https://en.wikipedia.org/w/index.php?title=Neponset,_Illinois&action=edit", "canonicalurl": "https://en.wikipedia.org/wiki/Neponset,_Illinois"}}}}