{"batchcomplete": "", "query": {"pages": {"136545": {"pageid": 136545, "ns": 0, "title": "New London, Texas", "contentmodel": "wikitext", "pagelanguage": "en", "pagelanguagehtmlcode": "en", "pagelanguagedir": "ltr", "touched": "2023-10-15T01:30:07Z", "lastrevid": 1180186480, "length": 10383, "talkid": 5187511, "fullurl": "https://en.wikipedia.org/wiki/New_London,_Texas", "editurl": "https://en.wikipedia.org/w/index.php?title=New_London,_Texas&action=edit", "canonicalurl": "https://en.wikipedia.org/wiki/New_London,_Texas"}}}}