{"batchcomplete": "", "query": {"pages": {"109832": {"pageid": 109832, "ns": 0, "title": "New Smyrna Beach, Florida", "contentmodel": "wikitext", "pagelanguage": "en", "pagelanguagehtmlcode": "en", "pagelanguagedir": "ltr", "touched": "2023-10-10T22:35:40Z", "lastrevid": 1178202962, "length": 36450, "watchers": 67, "talkid": 3510655, "fullurl": "https://en.wikipedia.org/wiki/New_Smyrna_Beach,_Florida", "editurl": "https://en.wikipedia.org/w/index.php?title=New_Smyrna_Beach,_Florida&action=edit", "canonicalurl": "https://en.wikipedia.org/wiki/New_Smyrna_Beach,_Florida"}}}}