{"batchcomplete": "", "query": {"pages": {"129448": {"pageid": 129448, "ns": 0, "title": "New London, Ohio", "contentmodel": "wikitext", "pagelanguage": "en", "pagelanguagehtmlcode": "en", "pagelanguagedir": "ltr", "touched": "2023-10-10T22:35:54Z", "lastrevid": 1167395787, "length": 11520, "talkid": 8377678, "fullurl": "https://en.wikipedia.org/wiki/New_London,_Ohio", "editurl": "https://en.wikipedia.org/w/index.php?title=New_London,_Ohio&action=edit", "canonicalurl": "https://en.wikipedia.org/wiki/New_London,_Ohio"}}}}