{"batchcomplete": "", "query": {"pages": {"122612": {"pageid": 122612, "ns": 0, "title": "Nixa, Missouri", "contentmodel": "wikitext", "pagelanguage": "en", "pagelanguagehtmlcode": "en", "pagelanguagedir": "ltr", "touched": "2023-10-16T00:54:35Z", "lastrevid": 1180339212, "length": 16724, "talkid": 3597192, "fullurl": "https://en.wikipedia.org/wiki/Nixa,_Missouri", "editurl": "https://en.wikipedia.org/w/index.php?title=Nixa,_Missouri&action=edit", "canonicalurl": "https://en.wikipedia.org/wiki/Nixa,_Missouri"}}}}