{"batchcomplete": "", "query": {"pages": {"118775": {"pageid": 118775, "ns": 0, "title": "Novi, Michigan", "contentmodel": "wikitext", "pagelanguage": "en", "pagelanguagehtmlcode": "en", "pagelanguagedir": "ltr", "touched": "2023-10-10T22:35:47Z", "lastrevid": 1173882814, "length": 56963, "watchers": 59, "talkid": 1262662, "fullurl": "https://en.wikipedia.org/wiki/Novi,_Michigan", "editurl": "https://en.wikipedia.org/w/index.php?title=Novi,_Michigan&action=edit", "canonicalurl": "https://en.wikipedia.org/wiki/Novi,_Michigan"}}}}