{"batchcomplete": "", "query": {"pages": {"108597": {"pageid": 108597, "ns": 0, "title": "Olathe, Colorado", "contentmodel": "wikitext", "pagelanguage": "en", "pagelanguagehtmlcode": "en", "pagelanguagedir": "ltr", "touched": "2023-10-10T22:35:39Z", "lastrevid": 1166210310, "length": 14270, "talkid": 1435934, "fullurl": "https://en.wikipedia.org/wiki/Olathe,_Colorado", "editurl": "https://en.wikipedia.org/w/index.php?title=Olathe,_Colorado&action=edit", "canonicalurl": "https://en.wikipedia.org/wiki/Olathe,_Colorado"}}}}