{"batchcomplete": "", "query": {"pages": {"106897": {"pageid": 106897, "ns": 0, "title": "Pollard, Arkansas", "contentmodel": "wikitext", "pagelanguage": "en", "pagelanguagehtmlcode": "en", "pagelanguagedir": "ltr", "touched": "2023-10-10T22:35:38Z", "lastrevid": 1165898343, "length": 7953, "talkid": 283001, "fullurl": "https://en.wikipedia.org/wiki/Pollard,_Arkansas", "editurl": "https://en.wikipedia.org/w/index.php?title=Pollard,_Arkansas&action=edit", "canonicalurl": "https://en.wikipedia.org/wiki/Pollard,_Arkansas"}}}}