{"batchcomplete": "", "query": {"pages": {"107892": {"pageid": 107892, "ns": 0, "title": "Portola, California", "contentmodel": "wikitext", "pagelanguage": "en", "pagelanguagehtmlcode": "en", "pagelanguagedir": "ltr", "touched": "2023-10-10T22:35:39Z", "lastrevid": 1171724568, "length": 18894, "talkid": 7571018, "fullurl": "https://en.wikipedia.org/wiki/Portola,_California", "editurl": "https://en.wikipedia.org/w/index.php?title=Portola,_California&action=edit", "canonicalurl": "https://en.wikipedia.org/wiki/Portola,_California"}}}}