{"batchcomplete": "", "query": {"pages": {"112555": {"pageid": 112555, "ns": 0, "title": "Poseyville, Indiana", "contentmodel": "wikitext", "pagelanguage": "en", "pagelanguagehtmlcode": "en", "pagelanguagedir": "ltr", "touched": "2023-10-10T22:35:42Z", "lastrevid": 1166229297, "length": 10757, "talkid": 2520351, "fullurl": "https://en.wikipedia.org/wiki/Poseyville,_Indiana", "editurl": "https://en.wikipedia.org/w/index.php?title=Poseyville,_Indiana&action=edit", "canonicalurl": "https://en.wikipedia.org/wiki/Poseyville,_Indiana"}}}}