{"batchcomplete": "", "query": {"pages": {"110845": {"pageid": 110845, "ns": 0, "title": "Princeton, Illinois", "contentmodel": "wikitext", "pagelanguage": "en", "pagelanguagehtmlcode": "en", "pagelanguagedir": "ltr", "touched": "2023-10-13T15:22:31Z", "lastrevid": 1165898778, "length": 27411, "talkid": 4461826, "fullurl": "https://en.wikipedia.org/wiki/Princeton,_Illinois", "editurl": "https://en.wikipedia.org/w/index.php?title=Princeton,_Illinois&action=edit", "canonicalurl": "https://en.wikipedia.org/wiki/Princeton,_Illinois"}}}}