{"batchcomplete": "", "query": {"pages": {"136621": {"pageid": 136621, "ns": 0, "title": "Rio Grande City, Texas", "contentmodel": "wikitext", "pagelanguage": "en", "pagelanguagehtmlcode": "en", "pagelanguagedir": "ltr", "touched": "2023-10-10T22:36:01Z", "lastrevid": 1173288619, "length": 17208, "talkid": 6173001, "fullurl": "https://en.wikipedia.org/wiki/Rio_Grande_City,_Texas", "editurl": "https://en.wikipedia.org/w/index.php?title=Rio_Grande_City,_Texas&action=edit", "canonicalurl": "https://en.wikipedia.org/wiki/Rio_Grande_City,_Texas"}}}}