{"batchcomplete": "", "query": {"pages": {"111227": {"pageid": 111227, "ns": 0, "title": "Rockbridge, Illinois", "contentmodel": "wikitext", "pagelanguage": "en", "pagelanguagehtmlcode": "en", "pagelanguagedir": "ltr", "touched": "2023-10-10T22:35:41Z", "lastrevid": 1167507703, "length": 8328, "talkid": 8679685, "fullurl": "https://en.wikipedia.org/wiki/Rockbridge,_Illinois", "editurl": "https://en.wikipedia.org/w/index.php?title=Rockbridge,_Illinois&action=edit", "canonicalurl": "https://en.wikipedia.org/wiki/Rockbridge,_Illinois"}}}}