{"batchcomplete": "", "query": {"pages": {"115821": {"pageid": 115821, "ns": 0, "title": "Rosepine, Louisiana", "contentmodel": "wikitext", "pagelanguage": "en", "pagelanguagehtmlcode": "en", "pagelanguagedir": "ltr", "touched": "2023-10-10T22:35:45Z", "lastrevid": 1169724568, "length": 10848, "talkid": 11192917, "fullurl": "https://en.wikipedia.org/wiki/Rosepine,_Louisiana", "editurl": "https://en.wikipedia.org/w/index.php?title=Rosepine,_Louisiana&action=edit", "canonicalurl": "https://en.wikipedia.org/wiki/Rosepine,_Louisiana"}}}}