{"batchcomplete": "", "query": {"pages": {"135873": {"pageid": 135873, "ns": 0, "title": "Round Top, Texas", "contentmodel": "wikitext", "pagelanguage": "en", "pagelanguagehtmlcode": "en", "pagelanguagedir": "ltr", "touched": "2023-10-10T22:36:00Z", "lastrevid": 1166230326, "length": 10170, "talkid": 6400733, "fullurl": "https://en.wikipedia.org/wiki/Round_Top,_Texas", "editurl": "https://en.wikipedia.org/w/index.php?title=Round_Top,_Texas&action=edit", "canonicalurl": "https://en.wikipedia.org/wiki/Round_Top,_Texas"}}}}