{"batchcomplete": "", "query": {"pages": {"124556": {"pageid": 124556, "ns": 0, "title": "Roxbury, New Hampshire", "contentmodel": "wikitext", "pagelanguage": "en", "pagelanguagehtmlcode": "en", "pagelanguagedir": "ltr", "touched": "2023-10-10T22:35:51Z", "lastrevid": 1166230347, "length": 9956, "talkid": 3422171, "fullurl": "https://en.wikipedia.org/wiki/Roxbury,_New_Hampshire", "editurl": "https://en.wikipedia.org/w/index.php?title=Roxbury,_New_Hampshire&action=edit", "canonicalurl": "https://en.wikipedia.org/wiki/Roxbury,_New_Hampshire"}}}}