{"batchcomplete": "", "query": {"pages": {"151227": {"pageid": 151227, "ns": 0, "title": "San Patricio, Texas", "contentmodel": "wikitext", "pagelanguage": "en", "pagelanguagehtmlcode": "en", "pagelanguagedir": "ltr", "touched": "2023-10-10T22:36:08Z", "lastrevid": 1165900767, "length": 11253, "talkid": 6401241, "fullurl": "https://en.wikipedia.org/wiki/San_Patricio,_Texas", "editurl": "https://en.wikipedia.org/w/index.php?title=San_Patricio,_Texas&action=edit", "canonicalurl": "https://en.wikipedia.org/wiki/San_Patricio,_Texas"}}}}