{"batchcomplete": "", "query": {"pages": {"107676": {"pageid": 107676, "ns": 0, "title": "San Dimas, California", "contentmodel": "wikitext", "pagelanguage": "en", "pagelanguagehtmlcode": "en", "pagelanguagedir": "ltr", "touched": "2023-10-10T22:35:39Z", "lastrevid": 1177626538, "length": 34244, "watchers": 57, "talkid": 2683646, "fullurl": "https://en.wikipedia.org/wiki/San_Dimas,_California", "editurl": "https://en.wikipedia.org/w/index.php?title=San_Dimas,_California&action=edit", "canonicalurl": "https://en.wikipedia.org/wiki/San_Dimas,_California"}}}}