{"batchcomplete": "", "query": {"pages": {"122486": {"pageid": 122486, "ns": 0, "title": "Savannah, Missouri", "contentmodel": "wikitext", "pagelanguage": "en", "pagelanguagehtmlcode": "en", "pagelanguagedir": "ltr", "touched": "2023-10-10T22:35:50Z", "lastrevid": 1165900925, "length": 11887, "talkid": 3613503, "fullurl": "https://en.wikipedia.org/wiki/Savannah,_Missouri", "editurl": "https://en.wikipedia.org/w/index.php?title=Savannah,_Missouri&action=edit", "canonicalurl": "https://en.wikipedia.org/wiki/Savannah,_Missouri"}}}}