{"batchcomplete": "", "query": {"pages": {"104757": {"pageid": 104757, "ns": 0, "title": "Skyline, Alabama", "contentmodel": "wikitext", "pagelanguage": "en", "pagelanguagehtmlcode": "en", "pagelanguagedir": "ltr", "touched": "2023-10-10T22:35:37Z", "lastrevid": 1166231421, "length": 8241, "talkid": 281269, "fullurl": "https://en.wikipedia.org/wiki/Skyline,_Alabama", "editurl": "https://en.wikipedia.org/w/index.php?title=Skyline,_Alabama&action=edit", "canonicalurl": "https://en.wikipedia.org/wiki/Skyline,_Alabama"}}}}