{"batchcomplete": "", "query": {"pages": {"91247": {"pageid": 91247, "ns": 0, "title": "Southampton County, Virginia", "contentmodel": "wikitext", "pagelanguage": "en", "pagelanguagehtmlcode": "en", "pagelanguagedir": "ltr", "touched": "2023-10-10T22:35:32Z", "lastrevid": 1153510493, "length": 16490, "talkid": 104291, "fullurl": "https://en.wikipedia.org/wiki/Southampton_County,_Virginia", "editurl": "https://en.wikipedia.org/w/index.php?title=Southampton_County,_Virginia&action=edit", "canonicalurl": "https://en.wikipedia.org/wiki/Southampton_County,_Virginia"}}}}