{"batchcomplete": "", "query": {"pages": {"138094": {"pageid": 138094, "ns": 0, "title": "Sprague, Washington", "contentmodel": "wikitext", "pagelanguage": "en", "pagelanguagehtmlcode": "en", "pagelanguagedir": "ltr", "touched": "2023-10-10T22:36:02Z", "lastrevid": 1165902637, "length": 15220, "talkid": 12205879, "fullurl": "https://en.wikipedia.org/wiki/Sprague,_Washington", "editurl": "https://en.wikipedia.org/w/index.php?title=Sprague,_Washington&action=edit", "canonicalurl": "https://en.wikipedia.org/wiki/Sprague,_Washington"}}}}