{"batchcomplete": "", "query": {"pages": {"119734": {"pageid": 119734, "ns": 0, "title": "Stacy, Minnesota", "contentmodel": "wikitext", "pagelanguage": "en", "pagelanguagehtmlcode": "en", "pagelanguagedir": "ltr", "touched": "2023-10-10T22:35:48Z", "lastrevid": 1173705341, "length": 9315, "talkid": 12279638, "fullurl": "https://en.wikipedia.org/wiki/Stacy,_Minnesota", "editurl": "https://en.wikipedia.org/w/index.php?title=Stacy,_Minnesota&action=edit", "canonicalurl": "https://en.wikipedia.org/wiki/Stacy,_Minnesota"}}}}