{"batchcomplete": "", "query": {"pages": {"116194": {"pageid": 116194, "ns": 0, "title": "Starks, Maine", "contentmodel": "wikitext", "pagelanguage": "en", "pagelanguagehtmlcode": "en", "pagelanguagedir": "ltr", "touched": "2023-10-10T22:35:45Z", "lastrevid": 1166330377, "length": 10392, "talkid": 14587555, "fullurl": "https://en.wikipedia.org/wiki/Starks,_Maine", "editurl": "https://en.wikipedia.org/w/index.php?title=Starks,_Maine&action=edit", "canonicalurl": "https://en.wikipedia.org/wiki/Starks,_Maine"}}}}