{"batchcomplete": "", "query": {"pages": {"123589": {"pageid": 123589, "ns": 0, "title": "Stevensville, Montana", "contentmodel": "wikitext", "pagelanguage": "en", "pagelanguagehtmlcode": "en", "pagelanguagedir": "ltr", "touched": "2023-10-10T22:35:50Z", "lastrevid": 1156601273, "length": 18221, "talkid": 9820966, "fullurl": "https://en.wikipedia.org/wiki/Stevensville,_Montana", "editurl": "https://en.wikipedia.org/w/index.php?title=Stevensville,_Montana&action=edit", "canonicalurl": "https://en.wikipedia.org/wiki/Stevensville,_Montana"}}}}