{"batchcomplete": "", "query": {"pages": {"117673": {"pageid": 117673, "ns": 0, "title": "Stockbridge Township, Michigan", "contentmodel": "wikitext", "pagelanguage": "en", "pagelanguagehtmlcode": "en", "pagelanguagedir": "ltr", "touched": "2023-10-10T22:35:46Z", "lastrevid": 1167678117, "length": 8586, "talkid": 16145162, "fullurl": "https://en.wikipedia.org/wiki/Stockbridge_Township,_Michigan", "editurl": "https://en.wikipedia.org/w/index.php?title=Stockbridge_Township,_Michigan&action=edit", "canonicalurl": "https://en.wikipedia.org/wiki/Stockbridge_Township,_Michigan"}}}}