{"batchcomplete": "", "query": {"pages": {"122930": {"pageid": 122930, "ns": 0, "title": "Stoutsville, Missouri", "contentmodel": "wikitext", "pagelanguage": "en", "pagelanguagehtmlcode": "en", "pagelanguagedir": "ltr", "touched": "2023-10-10T22:35:50Z", "lastrevid": 1167678469, "length": 8957, "talkid": 4774610, "fullurl": "https://en.wikipedia.org/wiki/Stoutsville,_Missouri", "editurl": "https://en.wikipedia.org/w/index.php?title=Stoutsville,_Missouri&action=edit", "canonicalurl": "https://en.wikipedia.org/wiki/Stoutsville,_Missouri"}}}}