{"batchcomplete": "", "query": {"pages": {"130680": {"pageid": 130680, "ns": 0, "title": "Sumpter, Oregon", "contentmodel": "wikitext", "pagelanguage": "en", "pagelanguagehtmlcode": "en", "pagelanguagedir": "ltr", "touched": "2023-10-10T22:35:55Z", "lastrevid": 1163489236, "length": 17701, "talkid": 8094161, "fullurl": "https://en.wikipedia.org/wiki/Sumpter,_Oregon", "editurl": "https://en.wikipedia.org/w/index.php?title=Sumpter,_Oregon&action=edit", "canonicalurl": "https://en.wikipedia.org/wiki/Sumpter,_Oregon"}}}}