{"batchcomplete": "", "query": {"pages": {"136313": {"pageid": 136313, "ns": 0, "title": "Three Rivers, Texas", "contentmodel": "wikitext", "pagelanguage": "en", "pagelanguagehtmlcode": "en", "pagelanguagedir": "ltr", "touched": "2023-10-10T22:36:01Z", "lastrevid": 1165904111, "length": 16324, "talkid": 6411968, "fullurl": "https://en.wikipedia.org/wiki/Three_Rivers,_Texas", "editurl": "https://en.wikipedia.org/w/index.php?title=Three_Rivers,_Texas&action=edit", "canonicalurl": "https://en.wikipedia.org/wiki/Three_Rivers,_Texas"}}}}