{"batchcomplete": "", "query": {"pages": {"150991": {"pageid": 150991, "ns": 0, "title": "Trafford, Pennsylvania", "contentmodel": "wikitext", "pagelanguage": "en", "pagelanguagehtmlcode": "en", "pagelanguagedir": "ltr", "touched": "2023-10-10T22:36:08Z", "lastrevid": 1158114947, "length": 13059, "talkid": 11072068, "fullurl": "https://en.wikipedia.org/wiki/Trafford,_Pennsylvania", "editurl": "https://en.wikipedia.org/w/index.php?title=Trafford,_Pennsylvania&action=edit", "canonicalurl": "https://en.wikipedia.org/wiki/Trafford,_Pennsylvania"}}}}