{"batchcomplete": "", "query": {"pages": {"110804": {"pageid": 110804, "ns": 0, "title": "Ursa, Illinois", "contentmodel": "wikitext", "pagelanguage": "en", "pagelanguagehtmlcode": "en", "pagelanguagedir": "ltr", "touched": "2023-10-10T22:35:41Z", "lastrevid": 1167741292, "length": 8429, "talkid": 4461714, "fullurl": "https://en.wikipedia.org/wiki/Ursa,_Illinois", "editurl": "https://en.wikipedia.org/w/index.php?title=Ursa,_Illinois&action=edit", "canonicalurl": "https://en.wikipedia.org/wiki/Ursa,_Illinois"}}}}