{"batchcomplete": "", "query": {"pages": {"113924": {"pageid": 113924, "ns": 0, "title": "Valeria, Iowa", "contentmodel": "wikitext", "pagelanguage": "en", "pagelanguagehtmlcode": "en", "pagelanguagedir": "ltr", "touched": "2023-10-10T22:35:43Z", "lastrevid": 1165905969, "length": 9783, "talkid": 6875679, "fullurl": "https://en.wikipedia.org/wiki/Valeria,_Iowa", "editurl": "https://en.wikipedia.org/w/index.php?title=Valeria,_Iowa&action=edit", "canonicalurl": "https://en.wikipedia.org/wiki/Valeria,_Iowa"}}}}