{"batchcomplete": "", "query": {"pages": {"150410": {"pageid": 150410, "ns": 0, "title": "Victor, Iowa", "contentmodel": "wikitext", "pagelanguage": "en", "pagelanguagehtmlcode": "en", "pagelanguagedir": "ltr", "touched": "2023-10-10T22:36:07Z", "lastrevid": 1165906210, "length": 13920, "talkid": 6875651, "fullurl": "https://en.wikipedia.org/wiki/Victor,_Iowa", "editurl": "https://en.wikipedia.org/w/index.php?title=Victor,_Iowa&action=edit", "canonicalurl": "https://en.wikipedia.org/wiki/Victor,_Iowa"}}}}