{"batchcomplete": "", "query": {"pages": {"122528": {"pageid": 122528, "ns": 0, "title": "Warsaw, Missouri", "contentmodel": "wikitext", "pagelanguage": "en", "pagelanguagehtmlcode": "en", "pagelanguagedir": "ltr", "touched": "2023-10-10T22:35:50Z", "lastrevid": 1165906658, "length": 17197, "talkid": 4713200, "fullurl": "https://en.wikipedia.org/wiki/Warsaw,_Missouri", "editurl": "https://en.wikipedia.org/w/index.php?title=Warsaw,_Missouri&action=edit", "canonicalurl": "https://en.wikipedia.org/wiki/Warsaw,_Missouri"}}}}