{"batchcomplete": "", "query": {"pages": {"21229975": {"pageid": 21229975, "ns": 0, "title": "West Orange, New Jersey", "contentmodel": "wikitext", "pagelanguage": "en", "pagelanguagehtmlcode": "en", "pagelanguagedir": "ltr", "touched": "2023-10-10T23:00:19Z", "lastrevid": 1174392854, "length": 145087, "watchers": 68, "talkid": 4620657, "fullurl": "https://en.wikipedia.org/wiki/West_Orange,_New_Jersey", "editurl": "https://en.wikipedia.org/w/index.php?title=West_Orange,_New_Jersey&action=edit", "canonicalurl": "https://en.wikipedia.org/wiki/West_Orange,_New_Jersey"}}}}