{"batchcomplete": "", "query": {"pages": {"104819": {"pageid": 104819, "ns": 0, "title": "West Jefferson, Alabama", "contentmodel": "wikitext", "pagelanguage": "en", "pagelanguagehtmlcode": "en", "pagelanguagedir": "ltr", "touched": "2023-10-10T22:35:37Z", "lastrevid": 1166333114, "length": 6554, "talkid": 281319, "fullurl": "https://en.wikipedia.org/wiki/West_Jefferson,_Alabama", "editurl": "https://en.wikipedia.org/w/index.php?title=West_Jefferson,_Alabama&action=edit", "canonicalurl": "https://en.wikipedia.org/wiki/West_Jefferson,_Alabama"}}}}