{"batchcomplete": "", "query": {"pages": {"122067": {"pageid": 122067, "ns": 0, "title": "Willernie, Minnesota", "contentmodel": "wikitext", "pagelanguage": "en", "pagelanguagehtmlcode": "en", "pagelanguagedir": "ltr", "touched": "2023-10-10T22:35:49Z", "lastrevid": 1165907668, "length": 8414, "talkid": 13281648, "fullurl": "https://en.wikipedia.org/wiki/Willernie,_Minnesota", "editurl": "https://en.wikipedia.org/w/index.php?title=Willernie,_Minnesota&action=edit", "canonicalurl": "https://en.wikipedia.org/wiki/Willernie,_Minnesota"}}}}