{"batchcomplete": "", "query": {"pages": {"120000": {"pageid": 120000, "ns": 0, "title": "Winnebago, Minnesota", "contentmodel": "wikitext", "pagelanguage": "en", "pagelanguagehtmlcode": "en", "pagelanguagedir": "ltr", "touched": "2023-10-15T19:53:32Z", "lastrevid": 1180303862, "length": 15158, "talkid": 12297402, "fullurl": "https://en.wikipedia.org/wiki/Winnebago,_Minnesota", "editurl": "https://en.wikipedia.org/w/index.php?title=Winnebago,_Minnesota&action=edit", "canonicalurl": "https://en.wikipedia.org/wiki/Winnebago,_Minnesota"}}}}