{"models": {"articlequality": {"version": "0.9.2"}}, "scores": {"1177815846": {"articlequality": {"score": {"prediction": "C", "probability": {"B": 0.22195906154453046, "C": 0.5014123628180122, "FA": 0.007110660693797216, "GA": 0.04431902304965634, "Start": 0.21987350924453558, "Stub": 0.005325382649468153}}}}}, "request_info": {"page_title": "East Pennsboro Township, Cumberland County, Pennsylvania", "lastrevid": 1177815846, "url": "https://en.wikipedia.org/wiki/East_Pennsboro_Township,_Cumberland_County,_Pennsylvania", "touched": "2023-10-10T22:35:57Z"}}